lattica_query/__init__.py
lattica_query/auth.py
lattica_query/lattica_query_client.py
lattica_query/performance_utils.py
lattica_query/query_toolkit.py
lattica_query/worker_api.py
lattica_query/dev_utils/lattica_query_client_local.py
lattica_query/serialization/api_serialization_utils.py
lattica_query/serialization/generic_pb2.py
lattica_query/serialization/hom_op_pb2.py
lattica_query/serialization/serialization_utils.py
lattica_query-1.2.0.dist-info/licenses/LICENSE.md
lattica_query-1.2.0.dist-info/METADATA
lattica_query-1.2.0.dist-info/WHEEL
lattica_query-1.2.0.dist-info/top_level.txt
lattica_query-1.2.0.dist-info/RECORD
