Metadata-Version: 2.4
Name: lattica-query
Version: 1.2.0
Summary: Client package for running inference queries on the LatticaAI platform
Author-email: "LatticaAI Inc." <support@lattica.ai>
Requires-Python: >=3.11
License-File: LICENSE.md
Requires-Dist: lattica-common>=0.7.0
Requires-Dist: lattica-fhe-core>=0.9.0
Requires-Dist: timeit-decorator>=2.0.8
Requires-Dist: python-dotenv==1.0.1
Requires-Dist: protobuf==5.27.1
Requires-Dist: numpy>=2.0.0
Requires-Dist: torch==2.9.1
Requires-Dist: pybind11>=2.13.6
Dynamic: license-file
